Metadata-Version: 2.1
Name: subgpt
Version: 0.0.1
Summary: Find subdomains with GPT, for free
Home-page: https://github.com/s0md3v/SubGPT
Download-URL: https://github.com/s0md3v/SubGPT/archive/v0.0.1.zip
Author: s0md3v
License: GNU Affero General Public License v3.0
Keywords: recon,subdomain,pentesting,gpt,hacking
Classifier: Topic :: Security
Classifier: Operating System :: OS Independent
Classifier: Programming Language :: Python :: 3
License-File: LICENSE
